{
	"pages": [{
		"path": "pages/login/login",
		"style": {
			"navigationBarTitleText": "Bug Tracker",
			"enablePullDownRefresh": false
		}

	}, {
		"path": "pages/index/index",
		"style": {
			"navigationBarTitleText": "Bug Tracker",
			"app-plus": {
				"titleNView": {
					"buttons": [{
							"fontSrc": "/static/uni.ttf",
							"text": "\ue504",
							"type": "none",
							"color": "rgb(0,0,0)",
							"fontSize": "22px",
							"float": "right"
						},
						{
							"fontSrc": "/static/uni.ttf",
							"text": "\ue408",
							"type": "none",
							"color": "rgb(0,0,0)",
							"fontSize": "22px",
							"float": "right"
						}
					]
				}
			}
		}
	}, {
		"path": "pages/devices/devices",
		"style": {
			"navigationBarTitleText": "Devices",
			"enablePullDownRefresh": false
		}
		
	}, {
		"path": "pages/device_edit/device_edit",
		"style": {
			"navigationBarTitleText": "Device Edit",
			"enablePullDownRefresh": false
		}

	}, {
		"path": "pages/bugs/bugs",
		"style": {
			"navigationBarTitleText": "Bug Tracker",
			"enablePullDownRefresh": false
		}
	
	}, {
		"path": "pages/bug_edit/bug_edit",
		"style": {
			"navigationBarTitleText": "Bug Tracker",
			"enablePullDownRefresh": false
		}

	}, {
		"path": "pages/about/about",
		"style": {
			"navigationBarTitleText": "About",
			"enablePullDownRefresh": false
		}

	}, {
		"path": "pages/share/share",
		"style": {
			"navigationBarTitleText": "Share",
			"enablePullDownRefresh": false
		}

	}, {
		"path": "pages/download/download",
		"style": {
			"navigationBarTitleText": "Download",
			"enablePullDownRefresh": false
		}

	}],
	"globalStyle": {
		"navigationBarTextStyle": "black",
		"navigationBarTitleText": "yikang",
		"navigationBarBackgroundColor": "#dee1e6",
		"backgroundColor": "#F8F8F8",
		"app-plus": {
			"background": "#efeff4"
		}
	}
}
